
{
    "text": "",      
    "list" : [
        {
            "text": "Email",
            "type": "email",
            "data": ""
        },
        {
            "text": "Telefon/Mobile",
            "type": "phone",
            "data": ""       
        },
        {
            "text": "Xing",
            "type": "",
            "data": ""       
        },
        {
            "text": "LinkedIn",
            "type": "",
            "data": ""       
        },
        {
            "text": "GitHub",
            "type": "",
            "data": ""       
        }
    ]
}

